Python3BiaozhunKuShilijiaochengFix1/README.md
Python3BiaozhunKuShilijiaochengFix1/__init__.py
Python3BiaozhunKuShilijiaochengFix1/__main__.py
Python3BiaozhunKuShilijiaochengFix1/file.epub
Python3BiaozhunKuShilijiaochengFix1/index.html
Python3BiaozhunKuShilijiaochengFix1/css/__init__.py
Python3BiaozhunKuShilijiaochengFix1/css/annotations.css
Python3BiaozhunKuShilijiaochengFix1/css/main.css
Python3BiaozhunKuShilijiaochengFix1/css/normalize.css
Python3BiaozhunKuShilijiaochengFix1/css/popup.css
Python3BiaozhunKuShilijiaochengFix1/font/__init__.py
Python3BiaozhunKuShilijiaochengFix1/font/fontello.eot
Python3BiaozhunKuShilijiaochengFix1/font/fontello.svg
Python3BiaozhunKuShilijiaochengFix1/font/fontello.ttf
Python3BiaozhunKuShilijiaochengFix1/font/fontello.woff
Python3BiaozhunKuShilijiaochengFix1/img/__init__.py
Python3BiaozhunKuShilijiaochengFix1/img/annotator-glyph-sprite.png
Python3BiaozhunKuShilijiaochengFix1/img/annotator-icon-sprite.png
Python3BiaozhunKuShilijiaochengFix1/img/apple-touch-icon.png
Python3BiaozhunKuShilijiaochengFix1/img/cancelfullscreen.png
Python3BiaozhunKuShilijiaochengFix1/img/close.png
Python3BiaozhunKuShilijiaochengFix1/img/fullscreen.png
Python3BiaozhunKuShilijiaochengFix1/img/loader.gif
Python3BiaozhunKuShilijiaochengFix1/img/menu-icon.png
Python3BiaozhunKuShilijiaochengFix1/img/save.png
Python3BiaozhunKuShilijiaochengFix1/img/saved.png
Python3BiaozhunKuShilijiaochengFix1/img/settings-s.png
Python3BiaozhunKuShilijiaochengFix1/img/settings.png
Python3BiaozhunKuShilijiaochengFix1/img/star.png
Python3BiaozhunKuShilijiaochengFix1/js/__init__.py
Python3BiaozhunKuShilijiaochengFix1/js/epub.js
Python3BiaozhunKuShilijiaochengFix1/js/epub.min.js
Python3BiaozhunKuShilijiaochengFix1/js/epub.min.map
Python3BiaozhunKuShilijiaochengFix1/js/hooks.min.js
Python3BiaozhunKuShilijiaochengFix1/js/hooks.min.map
Python3BiaozhunKuShilijiaochengFix1/js/reader.js
Python3BiaozhunKuShilijiaochengFix1/js/reader.js.map
Python3BiaozhunKuShilijiaochengFix1/js/reader.min.js
python_3_biaozhun_ku_shilijiaocheng_fix1-2025.3.24.0.dist-info/METADATA
python_3_biaozhun_ku_shilijiaocheng_fix1-2025.3.24.0.dist-info/WHEEL
python_3_biaozhun_ku_shilijiaocheng_fix1-2025.3.24.0.dist-info/entry_points.txt
python_3_biaozhun_ku_shilijiaocheng_fix1-2025.3.24.0.dist-info/top_level.txt
python_3_biaozhun_ku_shilijiaocheng_fix1-2025.3.24.0.dist-info/RECORD
